pkg1232/__init__.py
pkg1232/bar.py
pkg1232/foo.py
pkg1232/pkg.cfg
pkg1232-1.0.0.data/scripts/foo.py
pkg1232-1.0.0.dist-info/METADATA
pkg1232-1.0.0.dist-info/WHEEL
pkg1232-1.0.0.dist-info/top_level.txt
pkg1232-1.0.0.dist-info/RECORD
